[
    {
      "id": "#872157",
      "product": "Solid, Color Block Men Black Sports Shorts",
      "orderValue": "Rs. 1,359.00",
      "status": "Delivered",
      "orderedOn": "Aug 15, 2023",
      "deliveredOn": "Aug 15, 2023"
    },
    {
      "id": "#872324",
      "product": "Solid, Color Block Men Black Sports Shorts",
      "orderValue": "Rs. 5,234.00",
      "status": "Delivered",
      "orderedOn": "Aug 15, 2023",
      "deliveredOn": "Aug 15, 2023"
    },
    {
      "id": "#234523",
      "product": "Solid, Color Block Men Black Sports Shorts",
      "orderValue": "Rs. 1,313.00",
      "status": "Delivered",
      "orderedOn": "Aug 15, 2023",
      "deliveredOn": "Aug 15, 2023"
    }
  ]